reflutter-0.8.5.dist-info/licenses/LICENSE
src/__init__.py
src/utils.py
reflutter-0.8.5.dist-info/METADATA
reflutter-0.8.5.dist-info/WHEEL
reflutter-0.8.5.dist-info/entry_points.txt
reflutter-0.8.5.dist-info/top_level.txt
reflutter-0.8.5.dist-info/RECORD
